LICENSE
README.md
setup.py
bin/cctyper
bin/repeatTrain
bin/repeatType
cctyper/__init__.py
cctyper/blast.py
cctyper/castyping.py
cctyper/controller.py
cctyper/crisprcas.py
cctyper/hmmer.py
cctyper/minced.py
cctyper/plot.py
cctyper/prodigal.py
cctyper/repeat.py
cctyper/xgb.py
cctyper/xgbtrain.py
cctyper.egg-info/PKG-INFO
cctyper.egg-info/SOURCES.txt
cctyper.egg-info/dependency_links.txt
cctyper.egg-info/requires.txt
cctyper.egg-info/top_level.txt